lightning_trainer_utils/__init__.py
lightning_trainer_utils/train-model.py
lightning_trainer_utils/data_utils/__init__.py
lightning_trainer_utils/data_utils/data_loader.py
lightning_trainer_utils/data_utils/data_module.py
lightning_trainer_utils/trainer_utils/__init__.py
lightning_trainer_utils/trainer_utils/callbacks.py
lightning_trainer_utils/trainer_utils/ema.py
lightning_trainer_utils/trainer_utils/model_wrapper.py
lightning_trainer_utils/trainer_utils/optimizer_scheduler.py
lightning_trainer_utils-2025.5.26.15.18.dist-info/METADATA
lightning_trainer_utils-2025.5.26.15.18.dist-info/WHEEL
lightning_trainer_utils-2025.5.26.15.18.dist-info/top_level.txt
lightning_trainer_utils-2025.5.26.15.18.dist-info/RECORD
