Metadata-Version: 2.4
Name: lightning_trainer_utils
Version: 2025.5.26.15.18
Summary: A Python package for using PyTorch Lightning with custom callbacks and model wrappers.
Home-page: https://github.com/manavmahan/lightning-trainer-utils
Author: Manav Mahan Singh
Author-email: manav@genaec.ai
Requires-Python: >=3.11
Dynamic: author
Dynamic: author-email
Dynamic: description
Dynamic: description-content-type
Dynamic: home-page
Dynamic: requires-python
Dynamic: summary
